{
  "final_test_MAPE": 2.442503837056057,
  "final_median": 1.565543523132876,
  "final_p90": 5.0834976634058435,
  "stage1_test_MAPE": 3.3036001958674754,
  "stage2_test_MAPE": 2.4563406151154976,
  "stage3_test_MAPE": 2.442503837056057,
  "stage2_config": {
    "n_estimators": 500,
    "learning_rate": 0.05,
    "num_leaves": 31,
    "max_depth": 4,
    "min_child_samples": 80,
    "reg_lambda": 1.0,
    "objective": "regression_l1",
    "metric": "l1",
    "feature_fraction": 0.85,
    "bagging_fraction": 0.85,
    "bagging_freq": 5
  },
  "stage3_config": {
    "n_estimators": 300,
    "learning_rate": 0.03,
    "num_leaves": 15,
    "max_depth": 4,
    "min_child_samples": 120,
    "reg_lambda": 2.0,
    "objective": "regression_l1",
    "metric": "l1",
    "feature_fraction": 0.7,
    "bagging_fraction": 0.7,
    "bagging_freq": 5
  },
  "stage3_features": [
    "n_pin_PIN",
    "n_pin_inst",
    "n_pins",
    "n_pins_matched",
    "n_pins_total",
    "n_segments",
    "n_zero_l_wire",
    "nsq_M2",
    "nsq_M3",
    "nsq_M4",
    "nsq_M5",
    "nvian_VIA1_60SX44_68V_44H",
    "nvian_VIA2_44X58S_44H_44V",
    "nvian_VIA3_58SX44_44V_44H",
    "nvian_VIA4_44X58S_44H_44V",
    "one",
    "pin_nsq_M1",
    "rsq_M2",
    "rsq_M3",
    "rsq_M4",
    "pred_lin",
    "pred_s2",
    "log_pred_s2",
    "sqrt_pred_s2"
  ],
  "n_seeds_s2": 5,
  "n_seeds_s3": 3
}